LICENSE
MANIFEST.in
README
setup.cfg
setup.py
tests.py
pyunisend/__init__.py
pyunisend/pyunisend.py
pyunisend.egg-info/PKG-INFO
pyunisend.egg-info/SOURCES.txt
pyunisend.egg-info/dependency_links.txt
pyunisend.egg-info/requires.txt
pyunisend.egg-info/top_level.txt
pyunisend.egg-info/zip-safe