Metadata-Version: 1.0
Name: pyunisend
Version: 0.1.0
Summary: Wrapper API UniSender.com for Python
Home-page: https://github.com/klinkin/pyunisend
Author: Mike Klimin
Author-email: klinkin@gmail.com
License: MIT license
Download-URL: http://pypi.python.org/pypi/pyunisend/
Keywords: unisender api wrapper
Platform: any
Classifier: Development Status :: 3 - Alpha
Classifier: Intended Audience :: Developers
Classifier: License :: OSI Approved :: MIT License
Classifier: Natural Language :: Russian
Classifier: Natural Language :: English
Classifier: Operating System :: OS Independent
Classifier: Programming Language :: Python
Classifier: Programming Language :: Python :: 2
Classifier: Programming Language :: Python :: 2.5
Classifier: Programming Language :: Python :: 2.6
Classifier: Programming Language :: Python :: 2.7
Classifier: Topic :: Software Development :: Libraries :: Python Modules
